huaweicloudsdkmrs/__init__.py
huaweicloudsdkmrs/v1/__init__.py
huaweicloudsdkmrs/v1/mrs_async_client.py
huaweicloudsdkmrs/v1/mrs_client.py
huaweicloudsdkmrs/v1/model/__init__.py
huaweicloudsdkmrs/v1/model/add_jobs_req_v11.py
huaweicloudsdkmrs/v1/model/auto_scaling_policy.py
huaweicloudsdkmrs/v1/model/auto_scaling_policy_req_v11.py
huaweicloudsdkmrs/v1/model/available_tag.py
huaweicloudsdkmrs/v1/model/available_zone_v2.py
huaweicloudsdkmrs/v1/model/batch_create_cluster_tags_req.py
huaweicloudsdkmrs/v1/model/batch_create_cluster_tags_request.py
huaweicloudsdkmrs/v1/model/batch_create_cluster_tags_response.py
huaweicloudsdkmrs/v1/model/batch_delete_cluster_tags_req.py
huaweicloudsdkmrs/v1/model/batch_delete_cluster_tags_request.py
huaweicloudsdkmrs/v1/model/batch_delete_cluster_tags_response.py
huaweicloudsdkmrs/v1/model/bootstrap_script.py
huaweicloudsdkmrs/v1/model/cluster.py
huaweicloudsdkmrs/v1/model/cluster_scaling_params.py
huaweicloudsdkmrs/v1/model/cluster_scaling_req.py
huaweicloudsdkmrs/v1/model/component_amb.py
huaweicloudsdkmrs/v1/model/component_amb_v11.py
huaweicloudsdkmrs/v1/model/component_external_datasource.py
huaweicloudsdkmrs/v1/model/create_and_execute_job_request.py
huaweicloudsdkmrs/v1/model/create_and_execute_job_response.py
huaweicloudsdkmrs/v1/model/create_cluster_req_v11.py
huaweicloudsdkmrs/v1/model/create_cluster_request.py
huaweicloudsdkmrs/v1/model/create_cluster_response.py
huaweicloudsdkmrs/v1/model/create_cluster_tag_request.py
huaweicloudsdkmrs/v1/model/create_cluster_tag_response.py
huaweicloudsdkmrs/v1/model/create_scaling_policy_request.py
huaweicloudsdkmrs/v1/model/create_scaling_policy_response.py
huaweicloudsdkmrs/v1/model/create_tag_req.py
huaweicloudsdkmrs/v1/model/delete_cluster_request.py
huaweicloudsdkmrs/v1/model/delete_cluster_response.py
huaweicloudsdkmrs/v1/model/delete_cluster_tag_request.py
huaweicloudsdkmrs/v1/model/delete_cluster_tag_response.py
huaweicloudsdkmrs/v1/model/delete_job_execution_request.py
huaweicloudsdkmrs-3.1.184.dist-info/METADATA
huaweicloudsdkmrs-3.1.184.dist-info/WHEEL
huaweicloudsdkmrs-3.1.184.dist-info/licenses/LICENSE
huaweicloudsdkmrs-3.1.184.dist-info/RECORD
